otel_mcp/__init__.py
otel_mcp/api.py
otel_mcp/config.py
otel_mcp/models.py
otel_mcp/server.py
otel_mcp/telemetry.py
otel_mcp/backends/__init__.py
otel_mcp/backends/base.py
otel_mcp/backends/jaeger.py
otel_mcp-0.1.4.dist-info/METADATA
otel_mcp-0.1.4.dist-info/WHEEL
otel_mcp-0.1.4.dist-info/entry_points.txt
otel_mcp-0.1.4.dist-info/RECORD
