Metadata-Version: 2.4
Name: otel-mcp
Version: 0.1.4
Summary: MCP server for OpenTelemetry trace analysis during development
Project-URL: Repository, https://github.com/ryanm101/otel-mcp
Author: DIYTechnologist
License: Apache-2.0
Keywords: debugging,jaeger,mcp,model-context-protocol,observability,opentelemetry,tracing
Classifier: Development Status :: 3 - Alpha
Classifier: Intended Audience :: Developers
Classifier: Programming Language :: Python :: 3
Classifier: Programming Language :: Python :: 3.11
Classifier: Programming Language :: Python :: 3.12
Classifier: Topic :: System :: Monitoring
Requires-Python: >=3.11
Requires-Dist: fastapi<1.0.0,>=0.115.0
Requires-Dist: fastmcp<3.0.0,>=2.13.0
Requires-Dist: httpx<1.0.0,>=0.28.0
Requires-Dist: mcp<2.0.0,>=1.20.0
Requires-Dist: opentelemetry-api<2.0.0,>=1.29.0
Requires-Dist: opentelemetry-exporter-otlp<2.0.0,>=1.29.0
Requires-Dist: opentelemetry-instrumentation-fastapi>=0.50b0
Requires-Dist: opentelemetry-instrumentation-httpx>=0.50b0
Requires-Dist: opentelemetry-sdk<2.0.0,>=1.29.0
Requires-Dist: pydantic<3.0.0,>=2.12.0
Requires-Dist: python-dotenv<2.0.0,>=1.2.0
Requires-Dist: uvicorn<1.0.0,>=0.34.0
